st_repeating_field_group/__init__.py
st_repeating_field_group-0.2.0.dist-info/LICENSE
st_repeating_field_group-0.2.0.dist-info/METADATA
st_repeating_field_group-0.2.0.dist-info/WHEEL
st_repeating_field_group-0.2.0.dist-info/top_level.txt
st_repeating_field_group-0.2.0.dist-info/RECORD
