Metadata-Version: 2.1
Name: st-repeating-field-group
Version: 0.2.0
Summary: A Streamlit plugin for creating repeating field groups
Home-page: https://github.com/joey12725/st-repeating-field-group
Author: Joey Hersh
Author-email: joeyandpaige@gmail.com
Keywords: streamlit plugin repeating field group
Classifier: Development Status :: 3 - Alpha
Classifier: Intended Audience :: Developers
Classifier: License :: OSI Approved :: MIT License
Classifier: Programming Language :: Python :: 3
Classifier: Programming Language :: Python :: 3.7
Classifier: Programming Language :: Python :: 3.8
Classifier: Programming Language :: Python :: 3.9
Requires-Python: >=3.7
License-File: LICENSE
Requires-Dist: streamlit >=0.80.0
